gridjug/__init__.py
gridjug/grid_jug.py
gridjug/test/__init__.py
gridjug/test/failing.py
gridjug/test/primes.py
gridjug/test/test_gridjug.py
gridjug-0.4.0.dist-info/entry_points.txt
gridjug-0.4.0.dist-info/top_level.txt
gridjug-0.4.0.dist-info/namespace_packages.txt
gridjug-0.4.0.dist-info/METADATA
gridjug-0.4.0.dist-info/DESCRIPTION.rst
gridjug-0.4.0.dist-info/metadata.json
gridjug-0.4.0.dist-info/WHEEL
gridjug-0.4.0.dist-info/RECORD
