Metadata-Version: 2.0
Name: gridjug
Version: 0.4.0
Summary: A light-weight wrapper to run Jug with GridMap on a Grid Engine cluster
Home-page: http://gridjug.readthedocs.org
Author: Andreas Sorge
Author-email: gridjug@asorge.de
License: isc
Platform: UNKNOWN
Classifier: Development Status :: 3 - Alpha
Classifier: Intended Audience :: Science/Research
Classifier: License :: OSI Approved :: ISC License (ISCL)
Classifier: Programming Language :: Python
Classifier: Programming Language :: Python :: 2.7
Classifier: Programming Language :: Python :: 3.4
Classifier: Topic :: Scientific/Engineering
Requires-Dist: future
Requires-Dist: gridmap
Requires-Dist: jug
